local_tuya_domoticz_tools/__init__.py
local_tuya_domoticz_tools/logger.py
local_tuya_domoticz_tools/plugin/__init__.py
local_tuya_domoticz_tools/plugin/install.py
local_tuya_domoticz_tools/plugin/metadata.py
local_tuya_domoticz_tools/plugin/plugin.py
local_tuya_domoticz_tools/plugin/template.txt
local_tuya_domoticz_tools/types.py
local_tuya_domoticz_tools/units/__init__.py
local_tuya_domoticz_tools/units/base.py
local_tuya_domoticz_tools/units/ids.py
local_tuya_domoticz_tools/units/manager.py
local_tuya_domoticz_tools/units/selector_switch.py
local_tuya_domoticz_tools/units/set_point.py
local_tuya_domoticz_tools/units/switch.py
local_tuya_domoticz_tools/units/temperature.py
local_tuya_domoticz_tools/units/value_preprocessors.py
local_tuya_domoticz_tools-1.2.0.dist-info/LICENSE
local_tuya_domoticz_tools-1.2.0.dist-info/METADATA
local_tuya_domoticz_tools-1.2.0.dist-info/WHEEL
local_tuya_domoticz_tools-1.2.0.dist-info/RECORD
