Metadata-Version: 2.1
Name: local_tuya_domoticz_tools
Version: 1.2.0
Summary: Tools to create a Domoticz plugin for local-tuya devices.
Home-page: https://github.com/gpajot/local-tuya-domoticz-tools
License: MIT
Author: Gabriel Pajot
Author-email: gab@les-cactus.co
Requires-Python: >=3.8
Classifier: License :: OSI Approved :: MIT License
Classifier: Programming Language :: Python :: 3
Classifier: Programming Language :: Python :: 3.8
Classifier: Programming Language :: Python :: 3.9
Classifier: Programming Language :: Python :: 3.10
Classifier: Programming Language :: Python :: 3.11
Classifier: Programming Language :: Python :: 3.12
Requires-Dist: concurrent-tasks (>=1.4,<2)
Requires-Dist: local-tuya (>=3,<4)
Requires-Dist: xmltodict (>=0.13,<0.14)
Project-URL: Repository, https://github.com/gpajot/local-tuya-domoticz-tools
